tinyssb/__init__.py
tinyssb-0.0.1.dist-info/LICENSE
tinyssb-0.0.1.dist-info/METADATA
tinyssb-0.0.1.dist-info/WHEEL
tinyssb-0.0.1.dist-info/top_level.txt
tinyssb-0.0.1.dist-info/RECORD
