Metadata-Version: 2.1
Name: tinyssb
Version: 0.0.1
Summary: tinySSB - a compact version of Secure Scuttlebutt
Home-page: https://github.com/cn-uofbasel/tinyssb
Author: Christian Tschudin
Author-email: christian.tschudin@unibas.ch
License: UNKNOWN
Platform: UNKNOWN
Classifier: Programming Language :: Python :: 3
Classifier: License :: OSI Approved :: MIT License
Classifier: Operating System :: OS Independent
Requires-Python: >=3.7
License-File: LICENSE
